enet/__init__.py
enet/econnect.py
econnect-0.1.2.dist-info/LICENSE
econnect-0.1.2.dist-info/METADATA
econnect-0.1.2.dist-info/WHEEL
econnect-0.1.2.dist-info/top_level.txt
econnect-0.1.2.dist-info/RECORD
