Metadata-Version: 2.1
Name: econnect
Version: 0.1.2
Summary: Paquete para conectarse al Portal Cautivo de Etecsa en Cuba desde Python.
Home-page: https://github.com/TheMrAleX/econnect
Author: Alejandro Pérez Santana
Author-email: alejandroperezsantana55@gmail.com
Classifier: Development Status :: 4 - Beta
Classifier: Environment :: Console
Classifier: Intended Audience :: Developers
Classifier: License :: OSI Approved :: MIT License
Classifier: Natural Language :: Spanish
Classifier: Operating System :: OS Independent
Classifier: Programming Language :: Python
Classifier: Programming Language :: Python :: 3.12
Classifier: Topic :: Internet :: WWW/HTTP :: Session
License-File: LICENSE
Requires-Dist: httpx >=0.25.5
Requires-Dist: beautifulsoup4 >=4.12.2
